interprocess/__init__.py
interprocess/ipython.py
interprocess-0.0.1.data/scripts/xc
interprocess-0.0.1.dist-info/METADATA
interprocess-0.0.1.dist-info/WHEEL
interprocess-0.0.1.dist-info/top_level.txt
interprocess-0.0.1.dist-info/RECORD
